{
  "Rows": {
    "RowColumnAttachedInfos": {
      "0": {
        "GridRowColumnDefinition": {
          "DesignLengthInPixel": 25.0
        }
      },
      "1": {
        "GridRowColumnDefinition": {
          "DesignLengthInPixel": 25.0
        }
      }
    },
    "Count": 2,
    "DefaultSize": 25.0
  },
  "Cols": {
    "InLogicalVisibleIndexes": [
      39,
      40,
      41,
      42,
      43,
      44,
      45,
      46,
      47,
      48,
      49,
      50,
      51
    ],
    "Count": 52
  },
  "Values": {
    "0,0": "■",
    "0,40": "▼売上区分",
    "0,45": "▼PDF保存フラグ"
  },
  "AttachInfos": {
    "0,0": {
      "RulesGuidList": [
        "f4109a7a-5ee9-43a5-823a-43103bc3d96f"
      ]
    },
    "0,1": {
      "TemplateCellSource": "売上日",
      "RulesGuidList": [
        "c80aae58-6c1d-40ba-8329-017b9699d952"
      ]
    },
    "0,6": {
      "TemplateCellSource": "請求商品名",
      "RulesGuidList": [
        "87eac861-261e-4b87-b3ca-769f82c3db90"
      ]
    },
    "0,18": {
      "TemplateCellSource": "請求先名",
      "RulesGuidList": [
        "83c9bc24-defc-4338-94d2-a1364140bae9"
      ]
    },
    "0,30": {
      "TemplateCellSource": "税抜金額",
      "RulesGuidList": [
        "52e6e6f9-ad84-40c8-8684-6b9f07c0e408"
      ]
    },
    "0,34": {
      "TemplateCellSource": "請求日",
      "RulesGuidList": [
        "cf3c72c3-b699-47fd-98cd-3ac587d66e47"
      ]
    },
    "1,1": {
      "TemplateCellSource": "売掛区分名",
      "RulesGuidList": [
        "4bdcf638-7c87-4f8d-ba1b-f87713d4a0c4"
      ]
    },
    "1,6": {
      "TemplateCellSource": "請求備考",
      "RulesGuidList": [
        "4e2029f9-b994-4ce9-bc8a-15a1786c7466"
      ]
    },
    "1,18": {
      "TemplateCellSource": "住宅事業者名",
      "RulesGuidList": [
        "6a432974-2edf-47c7-be57-80fd07fba2a8"
      ]
    },
    "1,30": {
      "TemplateCellSource": "消費税額",
      "RulesGuidList": [
        "a5239c25-dc23-423f-9430-c80891259e24"
      ]
    },
    "1,34": {
      "TemplateCellSource": "回収予定日",
      "RulesGuidList": [
        "6d7b6673-d4b5-477f-8e5c-d6db319cf522"
      ]
    },
    "1,40": {
      "TemplateCellSource": "売上区分"
    },
    "1,45": {
      "TemplateCellSource": "PDF保存フラグ"
    }
  },
  "StyleDatas": {
    "Styles": [
      {
        "FontSize": 18.666666666666664,
        "Foreground": 0,
        "HorizontalAlignment": 1,
        "BorderBottom": null,
        "BorderRight": 0
      },
      {
        "FontSize": 12.0,
        "Formatter": 3,
        "HorizontalAlignment": 1,
        "BorderBottom": 0,
        "BorderTop": null
      },
      {
        "BorderBottom": 0,
        "BorderTop": null
      },
      {
        "BorderBottom": 0,
        "BorderTop": null,
        "BorderRight": 0
      },
      {
        "FontSize": 12.0,
        "TextIndent": 4,
        "BorderBottom": 0,
        "BorderTop": null
      },
      {
        "FontSize": 12.0,
        "TextIndent": 4,
        "BorderBottom": 0,
        "ShrinkToFit": true
      },
      {
        "BorderBottom": 0
      },
      {
        "BorderBottom": 0,
        "BorderRight": 0
      },
      {
        "BorderBottom": 0,
        "BorderTop": null,
        "BorderRight": null
      },
      {
        "FontSize": 12.0,
        "Formatter": 4,
        "HorizontalAlignment": 5,
        "BorderBottom": 0,
        "BorderTop": null
      },
      {
        "FontFamily": 6,
        "Formatter": 7
      },
      {
        "BorderRight": 0
      },
      {
        "FontSize": 12.0,
        "HorizontalAlignment": 1,
        "BorderTop": 0
      },
      {
        "BorderTop": 0
      },
      {
        "BorderTop": 0,
        "BorderRight": 0
      },
      {
        "FontSize": 12.0,
        "TextIndent": 4,
        "BorderTop": 0
      },
      {
        "FontSize": 12.0,
        "TextIndent": 4,
        "BorderTop": 0,
        "ShrinkToFit": true
      },
      {
        "BorderTop": 0,
        "BorderRight": null
      },
      {
        "FontSize": 12.0,
        "Formatter": 4,
        "HorizontalAlignment": 5,
        "BorderTop": 0
      },
      {
        "FontFamily": 6,
        "FontSize": 12.0,
        "Formatter": 3,
        "HorizontalAlignment": 1,
        "BorderBottom": null,
        "BorderTop": 0
      },
      {
        "FontFamily": 6,
        "BorderBottom": null,
        "BorderTop": 0
      },
      {
        "Background": 8,
        "FontFamily": 6
      },
      {
        "FontFamily": 6
      }
    ],
    "Types": {
      "Strs": [
        "Accent 5 40",
        "Center",
        "Background 1 -15",
        "yyyy/MM/dd",
        " ¥#,##0_);[Red] ¥(#,##0)",
        "Right",
        "Body",
        "[AUTO]General",
        "#FFFFFF00"
      ],
      "Borders": [
        {
          "Color": 2
        }
      ]
    },
    "CellStyles": {
      "0,0": 0,
      "0,1": 1,
      "0,2": 2,
      "0,3": 2,
      "0,4": 2,
      "0,5": 3,
      "0,6": 4,
      "0,7": 2,
      "0,8": 2,
      "0,9": 2,
      "0,10": 2,
      "0,11": 2,
      "0,12": 2,
      "0,13": 2,
      "0,14": 2,
      "0,15": 2,
      "0,16": 2,
      "0,17": 3,
      "0,18": 5,
      "0,19": 6,
      "0,20": 6,
      "0,21": 6,
      "0,22": 6,
      "0,23": 6,
      "0,24": 6,
      "0,25": 6,
      "0,26": 6,
      "0,27": 6,
      "0,28": 7,
      "0,29": 8,
      "0,30": 9,
      "0,31": 2,
      "0,32": 2,
      "0,33": 3,
      "0,34": 1,
      "0,35": 2,
      "0,36": 2,
      "0,37": 2,
      "0,38": 2,
      "0,45": 10,
      "1,0": 11,
      "1,1": 12,
      "1,2": 13,
      "1,3": 13,
      "1,4": 13,
      "1,5": 14,
      "1,6": 15,
      "1,7": 13,
      "1,8": 13,
      "1,9": 13,
      "1,10": 13,
      "1,11": 13,
      "1,12": 13,
      "1,13": 13,
      "1,14": 13,
      "1,15": 13,
      "1,16": 13,
      "1,17": 14,
      "1,18": 16,
      "1,19": 13,
      "1,20": 13,
      "1,21": 13,
      "1,22": 13,
      "1,23": 13,
      "1,24": 13,
      "1,25": 13,
      "1,26": 13,
      "1,27": 13,
      "1,28": 14,
      "1,29": 17,
      "1,30": 18,
      "1,31": 13,
      "1,32": 13,
      "1,33": 14,
      "1,34": 19,
      "1,35": 20,
      "1,36": 20,
      "1,37": 20,
      "1,38": 20,
      "1,40": 21,
      "1,45": 21,
      "1,46": 22,
      "1,47": 22
    },
    "SheetStyle": {
      "FontFamily": 6
    }
  },
  "Spans": [
    "0,1,1,5",
    "0,6,1,12",
    "1,6,1,12",
    "0,34,1,5",
    "1,34,1,5",
    "0,18,1,11",
    "1,18,1,11",
    "1,30,1,4",
    "0,30,1,4",
    "1,40,1,3",
    "1,45,1,3",
    "1,1,1,5"
  ],
  "PageInfo": {
    "$type": "Forguncy.Model.Pages.TemplatePage, ServerDesignerCommon",
    "ParentPageName": "物件詳細_請求_内容",
    "ConditionFormatRulesCollection": {
      "Rules": [
        {
          "$type": "Forguncy.ConditionFormat.FormulaRule, ServerDesignerCommon",
          "Formula": {
            "$type": "Forguncy.Model.FormulaReferObject, ServerDesignerCommon",
            "SerializeProperty": "=e094a54a0d6b4a7e93a549eed584223!$AT$2=1"
          },
          "GUID": "f4109a7a-5ee9-43a5-823a-43103bc3d96f",
          "StyleInfo": {
            "Foreground": "Text 2 40",
            "Underline": null,
            "Strikethrough": null
          }
        },
        {
          "$type": "Forguncy.ConditionFormat.FormulaRule, ServerDesignerCommon",
          "Formula": {
            "$type": "Forguncy.Model.FormulaReferObject, ServerDesignerCommon",
            "SerializeProperty": "=VALUE(e094a54a0d6b4a7e93a549eed584223!AO2)=2"
          },
          "Priority": 1,
          "GUID": "c80aae58-6c1d-40ba-8329-017b9699d952",
          "StyleInfo": {
            "Foreground": "#FFFF0000",
            "Underline": null,
            "Strikethrough": null
          }
        },
        {
          "$type": "Forguncy.ConditionFormat.FormulaRule, ServerDesignerCommon",
          "Formula": {
            "$type": "Forguncy.Model.FormulaReferObject, ServerDesignerCommon",
            "SerializeProperty": "=VALUE(e094a54a0d6b4a7e93a549eed584223!AO2)=2"
          },
          "Priority": 2,
          "GUID": "87eac861-261e-4b87-b3ca-769f82c3db90",
          "StyleInfo": {
            "Foreground": "#FFFF0000",
            "Underline": null,
            "Strikethrough": null
          }
        },
        {
          "$type": "Forguncy.ConditionFormat.FormulaRule, ServerDesignerCommon",
          "Formula": {
            "$type": "Forguncy.Model.FormulaReferObject, ServerDesignerCommon",
            "SerializeProperty": "=VALUE(e094a54a0d6b4a7e93a549eed584223!AO2)=2"
          },
          "Priority": 3,
          "GUID": "83c9bc24-defc-4338-94d2-a1364140bae9",
          "StyleInfo": {
            "Foreground": "#FFFF0000",
            "Underline": null,
            "Strikethrough": null
          }
        },
        {
          "$type": "Forguncy.ConditionFormat.FormulaRule, ServerDesignerCommon",
          "Formula": {
            "$type": "Forguncy.Model.FormulaReferObject, ServerDesignerCommon",
            "SerializeProperty": "=VALUE(e094a54a0d6b4a7e93a549eed584223!AO2)=2"
          },
          "Priority": 4,
          "GUID": "52e6e6f9-ad84-40c8-8684-6b9f07c0e408",
          "StyleInfo": {
            "Foreground": "#FFFF0000",
            "Underline": null,
            "Strikethrough": null
          }
        },
        {
          "$type": "Forguncy.ConditionFormat.FormulaRule, ServerDesignerCommon",
          "Formula": {
            "$type": "Forguncy.Model.FormulaReferObject, ServerDesignerCommon",
            "SerializeProperty": "=VALUE(e094a54a0d6b4a7e93a549eed584223!AO2)=2"
          },
          "Priority": 5,
          "GUID": "cf3c72c3-b699-47fd-98cd-3ac587d66e47",
          "StyleInfo": {
            "Foreground": "#FFFF0000",
            "Underline": null,
            "Strikethrough": null
          }
        },
        {
          "$type": "Forguncy.ConditionFormat.FormulaRule, ServerDesignerCommon",
          "Formula": {
            "$type": "Forguncy.Model.FormulaReferObject, ServerDesignerCommon",
            "SerializeProperty": "=VALUE(e094a54a0d6b4a7e93a549eed584223!AO2)=2"
          },
          "Priority": 6,
          "GUID": "4bdcf638-7c87-4f8d-ba1b-f87713d4a0c4",
          "StyleInfo": {
            "Foreground": "#FFFF0000",
            "Underline": null,
            "Strikethrough": null
          }
        },
        {
          "$type": "Forguncy.ConditionFormat.FormulaRule, ServerDesignerCommon",
          "Formula": {
            "$type": "Forguncy.Model.FormulaReferObject, ServerDesignerCommon",
            "SerializeProperty": "=VALUE(e094a54a0d6b4a7e93a549eed584223!AO2)=2"
          },
          "Priority": 7,
          "GUID": "4e2029f9-b994-4ce9-bc8a-15a1786c7466",
          "StyleInfo": {
            "Foreground": "#FFFF0000",
            "Underline": null,
            "Strikethrough": null
          }
        },
        {
          "$type": "Forguncy.ConditionFormat.FormulaRule, ServerDesignerCommon",
          "Formula": {
            "$type": "Forguncy.Model.FormulaReferObject, ServerDesignerCommon",
            "SerializeProperty": "=VALUE(e094a54a0d6b4a7e93a549eed584223!AO2)=2"
          },
          "Priority": 8,
          "GUID": "6a432974-2edf-47c7-be57-80fd07fba2a8",
          "StyleInfo": {
            "Foreground": "#FFFF0000",
            "Underline": null,
            "Strikethrough": null
          }
        },
        {
          "$type": "Forguncy.ConditionFormat.FormulaRule, ServerDesignerCommon",
          "Formula": {
            "$type": "Forguncy.Model.FormulaReferObject, ServerDesignerCommon",
            "SerializeProperty": "=VALUE(e094a54a0d6b4a7e93a549eed584223!AO2)=2"
          },
          "Priority": 9,
          "GUID": "a5239c25-dc23-423f-9430-c80891259e24",
          "StyleInfo": {
            "Foreground": "#FFFF0000",
            "Underline": null,
            "Strikethrough": null
          }
        },
        {
          "$type": "Forguncy.ConditionFormat.FormulaRule, ServerDesignerCommon",
          "Formula": {
            "$type": "Forguncy.Model.FormulaReferObject, ServerDesignerCommon",
            "SerializeProperty": "=VALUE(e094a54a0d6b4a7e93a549eed584223!AO2)=2"
          },
          "Priority": 10,
          "GUID": "6d7b6673-d4b5-477f-8e5c-d6db319cf522",
          "StyleInfo": {
            "Foreground": "#FFFF0000",
            "Underline": null,
            "Strikethrough": null
          }
        }
      ]
    }
  },
  "PrintInfo": {
    "PaperSize": {},
    "Margin": {}
  }
}//QZztXMCP42xJ6ycS0cGVqkmrEbiHP9J3hoGMfKtSDPLq4gsN7x0vRLEsyzLQk6km15knyoi7HHF3YfL92DQCQRHvE755/DoHzntjdmp6Xl4kVq6Evg08u7Wkylr4U1csrVIa9QXyVamZvDrIyZrtU4Ph12o43II8GaMPmW/xc3/X+M2e09Ne84Vha3BfqnN8U9RA4dP/WotWwRW8h0povPND+ueKvakOqWqccL/arpHciwD+oTwvPT//UdDBnEQHuakWKeXT3R849MbhBa4wA/PHYWyttHi93CKvcmc8b7ddmzkPS6En2x2nDkWm3ikscVshN9DGARayRgLw9jJzhpQZfGmn1hKpCKa+/b44+EbwmLEp9OW8RrLqxUCAbj3OV3DzaUyQtDOqQwaa/exjwZk7DhdGj5gwA2dbTC5DLA6jEMnJybRgjWeeLoBPYgoQyUvUBUXXJU2BV8XpjtXJ3FV3uG/wuI/4+BfCvgiOwW1lqvHjflyvF1lMP8gQLPRtkcns9muc+XdjxzAKVc9nQEAwnUItgzuJrASLQ7UNSnpwIEmGRHiv8GURv79sioz1agMXuLkmGtcVD+NzILt/VNFsRocn9u41ISXWLSBEIxWcjYbmRuKSgT64YGLA41aTc5lIP+wEerV51jWHAGQF8ZtiCWbMlaBNam6AOIKhRDWH7JbmXBmL5ZTGbmxoNuwybMug58CtrvNWUf/BnNTCDa2WhUBl3iPnRYulklSxvHUu5uAGWOlPKmRMFG11ux1VC9bMpbdTFOr83fQXghR0cEVozeOTUryCXm01KHn1ONlT8lbTwW13I67OaMqn3QV67FWwB9DpeGhqMRpzp4G5+MGf1Y/7P/ThtfIX4j8S530GVOy2GlpavS1OzQTZjEskzGtJFmG07UnctyeFnZTjbw==|920